poetry2rye/__init__.py
poetry2rye/convert.py
poetry2rye/error.py
poetry2rye/main.py
poetry2rye/project.py
poetry2rye/utils.py
poetry2rye-0.3.1.dist-info/METADATA
poetry2rye-0.3.1.dist-info/WHEEL
poetry2rye-0.3.1.dist-info/entry_points.txt
poetry2rye-0.3.1.dist-info/licenses/LICENSE
poetry2rye-0.3.1.dist-info/RECORD
