Metadata-Version: 2.3
Name: poetry2rye
Version: 0.3.1
Summary: A simple tool to migrate your Poetry project to rye
Author-email: nahco314 <nahco3_ta@yahoo.co.jp>
License-File: LICENSE
Requires-Python: >=3.11
Requires-Dist: poetry-core>=1.9.0
Requires-Dist: pydantic~=1.10.8
Requires-Dist: pyproject-parser~=0.11.0
Requires-Dist: python-slugify~=8.0.1
Requires-Dist: tomlkit~=0.11.8
Requires-Dist: typing-extensions>=4.11.0
